puda_drivers/__init__.py
puda_drivers/py.typed
puda_drivers/core/__init__.py
puda_drivers/core/logging.py
puda_drivers/core/position.py
puda_drivers/core/serialcontroller.py
puda_drivers/cv/__init__.py
puda_drivers/cv/camera.py
puda_drivers/labware/MEA_cell_MTP.json
puda_drivers/labware/__init__.py
puda_drivers/labware/labware.py
puda_drivers/labware/opentrons_96_tiprack_300ul.json
puda_drivers/labware/polyelectric_8_wellplate_30000ul.json
puda_drivers/labware/trash_bin.json
puda_drivers/machines/__init__.py
puda_drivers/machines/first.py
puda_drivers/measure/electrode.py
puda_drivers/move/__init__.py
puda_drivers/move/deck.py
puda_drivers/move/gcode.py
puda_drivers/move/grbl/__init__.py
puda_drivers/move/grbl/api.py
puda_drivers/move/grbl/constants.py
puda_drivers/transfer/liquid/sartorius/__init__.py
puda_drivers/transfer/liquid/sartorius/api.py
puda_drivers/transfer/liquid/sartorius/constants.py
puda_drivers/transfer/liquid/sartorius/rLine.py
puda_drivers-0.0.19.dist-info/METADATA
puda_drivers-0.0.19.dist-info/WHEEL
puda_drivers-0.0.19.dist-info/licenses/LICENSE
puda_drivers-0.0.19.dist-info/RECORD
