Metadata-Version: 2.4
Name: puda-drivers
Version: 0.0.19
Summary: Hardware drivers for the PUDA platform.
Project-URL: Homepage, https://github.com/PUDAP/puda
Project-URL: Issues, https://github.com/PUDAP/puda/issues
Author-email: zhao <20024592+agentzhao@users.noreply.github.com>
License-Expression: MIT
License-File: LICENSE
Classifier: Intended Audience :: Developers
Classifier: Intended Audience :: Science/Research
Classifier: Operating System :: OS Independent
Classifier: Programming Language :: Python :: 3
Classifier: Programming Language :: Python :: 3.14
Classifier: Topic :: Software Development :: Libraries :: Python Modules
Classifier: Topic :: System :: Hardware
Requires-Python: >=3.10
Requires-Dist: nats-py>=2.12.0
Requires-Dist: opencv-python>=4.12.0.88
Requires-Dist: pyserial~=3.5
